lora.py
lora_modem_abz-1.1.3.dist-info/LICENSE
lora_modem_abz-1.1.3.dist-info/METADATA
lora_modem_abz-1.1.3.dist-info/WHEEL
lora_modem_abz-1.1.3.dist-info/entry_points.txt
lora_modem_abz-1.1.3.dist-info/top_level.txt
lora_modem_abz-1.1.3.dist-info/RECORD
