Metadata-Version: 2.1
Name: lora-modem-abz
Version: 1.1.3
Summary: Python library for the Murata TypeABZ LoRaWAN modem
Home-page: https://github.com/hardwario/lora-modem-abz
Author: Jan Janak
Author-email: jan@janakj.org
License: BSD 3-Clause License
Keywords: iot,lora,lorawan,lpwan,lorawan-device,firmware,stm32
Classifier: Programming Language :: Python :: 3
Classifier: Environment :: Console
Classifier: License :: OSI Approved :: BSD License
Classifier: Topic :: Communications
Classifier: Topic :: Software Development :: Embedded Systems
Classifier: Topic :: System :: Networking
Classifier: Topic :: Utilities
License-File: LICENSE
Requires-Dist: click
Requires-Dist: pymitter
Requires-Dist: pyserial
Requires-Dist: tabulate
